<?xml version="1.0" encoding="UTF-8"?>
<GenRun Id="synth_1" LaunchPart="xc7k70tfbv676-1" LaunchTime="1599084005">
  <File Type="PA-TCL" Name="mod_m_up_dn_count.tcl"/>
  <File Type="REPORTS-TCL" Name="mod_m_up_dn_count_reports.tcl"/>
  <File Type="RDS-RDS" Name="mod_m_up_dn_count.vds"/>
  <File Type="RDS-UTIL" Name="mod_m_up_dn_count_utilization_synth.rpt"/>
  <File Type="RDS-UTIL-PB" Name="mod_m_up_dn_count_utilization_synth.pb"/>
  <File Type="RDS-DCP" Name="mod_m_up_dn_count.dcp"/>
  <FileSet Name="sources" Type="DesignSrcs" RelSrcDir="$PSRCDIR/sources_1">
    <Filter Type="Srcs"/>
    <File Path="$PPRDIR/../design_sources/my_packages/ieee_2008/math_real.vhdl">
      <FileInfo>
        <Attr Name="UsedIn" Val="synthesis"/>
        <Attr Name="UsedIn" Val="simulation"/>
      </FileInfo>
    </File>
    <File Path="$PPRDIR/../design_sources/my_packages/ieee_2008/math_real-body.vhdl">
      <FileInfo>
        <Attr Name="UsedIn" Val="synthesis"/>
        <Attr Name="UsedIn" Val="simulation"/>
      </FileInfo>
    </File>
    <File Path="$PPRDIR/../design_sources/my_packages/my_package.vhd">
      <FileInfo>
        <Attr Name="UsedIn" Val="synthesis"/>
        <Attr Name="UsedIn" Val="simulation"/>
      </FileInfo>
    </File>
    <File Path="$PPRDIR/../design_sources/my_packages/my_package-body.vhd">
      <FileInfo>
        <Attr Name="UsedIn" Val="synthesis"/>
        <Attr Name="UsedIn" Val="simulation"/>
      </FileInfo>
    </File>
    <File Path="$PPRDIR/../design_sources/mod_m_up_dn_count.vhd">
      <FileInfo>
        <Attr Name="UsedIn" Val="synthesis"/>
        <Attr Name="UsedIn" Val="simulation"/>
      </FileInfo>
    </File>
    <Config>
      <Option Name="DesignMode" Val="RTL"/>
      <Option Name="TopModule" Val="mod_m_up_dn_count"/>
      <Option Name="TopAutoSet" Val="TRUE"/>
    </Config>
  </FileSet>
  <FileSet Name="constrs_in" Type="Constrs" RelSrcDir="$PSRCDIR/constrs_1">
    <Filter Type="Constrs"/>
    <Config>
      <Option Name="ConstrsType" Val="XDC"/>
    </Config>
  </FileSet>
  <FileSet Name="utils" Type="Utils" RelSrcDir="$PSRCDIR/utils_1">
    <Filter Type="Utils"/>
    <Config>
      <Option Name="TopAutoSet" Val="TRUE"/>
    </Config>
  </FileSet>
  <Strategy Version="1" Minor="2">
    <StratHandle Name="Vivado Synthesis Defaults" Flow="Vivado Synthesis 2019"/>
    <Step Id="synth_design"/>
  </Strategy>
</GenRun>
